compress_field/__init__.py
compress_field/base.py
compress_field/fieldfiles.py
compress_field/models.py
compress_field/tasks.py
django_compress_field-0.10.2.dist-info/LICENSE
django_compress_field-0.10.2.dist-info/METADATA
django_compress_field-0.10.2.dist-info/WHEEL
django_compress_field-0.10.2.dist-info/top_level.txt
django_compress_field-0.10.2.dist-info/RECORD
