Metadata-Version: 1.1
Name: django-compress-field
Version: 0.10.2
Summary: Automantic compress files after upload
Home-page: https://github.com/valdergallo/django-compress-field
Author: valdergallo
Author-email: valdergallo@gmail.com
License: FREEBSD
Download-URL: https://github.com/valdergallo/django-compress-field/tarball/v0.10.2/
Keywords: django,compress,field,zip,tar,gzip
Platform: any
Classifier: Framework :: Django
Classifier: Operating System :: OS Independent
Classifier: Topic :: Utilities
Classifier: Programming Language :: Python
Classifier: Programming Language :: Python :: 2.6
Classifier: Programming Language :: Python :: 2.7
Classifier: Programming Language :: Python :: 3.6
Classifier: Programming Language :: Python :: 3.7
